{"nodes": [{"id": "d_travelbuddy_lib_screens_auth_screen_dart", "label": "auth_screen.dart", "file_type": "code", "source_file": "lib/screens/auth_screen.dart", "source_location": null}, {"id": "screens_auth_screen_authscreen", "label": "AuthScreen", "file_type": "code", "source_file": "lib/screens/auth_screen.dart", "source_location": null}, {"id": "statefulwidget", "label": "StatefulWidget", "file_type": "code", "source_file": null, "source_location": null}, {"id": "screens_auth_screen_authscreenstate", "label": "_AuthScreenState", "file_type": "code", "source_file": "lib/screens/auth_screen.dart", "source_location": null}, {"id": "state", "label": "State", "file_type": "code", "source_file": null, "source_location": null}, {"id": "authscreen", "label": "AuthScreen", "file_type": "code", "source_file": null, "source_location": null}, {"id": "screens_auth_screen_isloading", "label": "_isLoading", "file_type": "code", "source_file": "lib/screens/auth_screen.dart", "source_location": null}, {"id": "screens_auth_screen_initialized", "label": "_initialized", "file_type": "code", "source_file": "lib/screens/auth_screen.dart", "source_location": null}, {"id": "static_bool", "label": "static bool", "file_type": "code", "source_file": null, "source_location": null}, {"id": "screens_auth_screen_createstate", "label": "createState", "file_type": "code", "source_file": "lib/screens/auth_screen.dart", "source_location": null}, {"id": "screens_auth_screen_signinwithgoogle", "label": "_signInWithGoogle", "file_type": "code", "source_file": "lib/screens/auth_screen.dart", "source_location": null}, {"id": "screens_auth_screen_build", "label": "build", "file_type": "code", "source_file": "lib/screens/auth_screen.dart", "source_location": null}, {"id": "screens_auth_screen_featurechip", "label": "_featureChip", "file_type": "code", "source_file": "lib/screens/auth_screen.dart", "source_location": null}, {"id": "package_flutter_material_dart", "label": "package:flutter/material.dart", "file_type": "code", "source_file": null, "source_location": null}, {"id": "package_flutter_foundation_dart", "label": "package:flutter/foundation.dart", "file_type": "code", "source_file": null, "source_location": null}, {"id": "package_firebase_auth_firebase_auth_dart", "label": "package:firebase_auth/firebase_auth.dart", "file_type": "code", "source_file": null, "source_location": null}, {"id": "package_google_sign_in_google_sign_in_dart", "label": "package:google_sign_in/google_sign_in.dart", "file_type": "code", "source_file": null, "source_location": null}, {"id": "package_google_fonts_google_fonts_dart", "label": "package:google_fonts/google_fonts.dart", "file_type": "code", "source_file": null, "source_location": null}, {"id": "home_screen_dart", "label": "home_screen.dart", "file_type": "code", "source_file": null, "source_location": null}], "edges": [{"source": "d_travelbuddy_lib_screens_auth_screen_dart", "target": "screens_auth_screen_authscreen", "relation": "defines", "confidence": "EXTRACTED", "confidence_score": 1.0, "source_file": "lib/screens/auth_screen.dart", "source_location": null, "weight": 1.0}, {"source": "screens_auth_screen_authscreen", "target": "statefulwidget", "relation": "inherits", "confidence": "EXTRACTED", "confidence_score": 1.0, "source_file": "lib/screens/auth_screen.dart", "source_location": null, "weight": 1.0}, {"source": "d_travelbuddy_lib_screens_auth_screen_dart", "target": "screens_auth_screen_authscreenstate", "relation": "defines", "confidence": "EXTRACTED", "confidence_score": 1.0, "source_file": "lib/screens/auth_screen.dart", "source_location": null, "weight": 1.0}, {"source": "screens_auth_screen_authscreenstate", "target": "state", "relation": "inherits", "confidence": "EXTRACTED", "confidence_score": 1.0, "source_file": "lib/screens/auth_screen.dart", "source_location": null, "weight": 1.0}, {"source": "screens_auth_screen_authscreenstate", "target": "authscreen", "relation": "references", "confidence": "EXTRACTED", "confidence_score": 1.0, "source_file": "lib/screens/auth_screen.dart", "source_location": null, "weight": 1.0}, {"source": "d_travelbuddy_lib_screens_auth_screen_dart", "target": "screens_auth_screen_isloading", "relation": "defines", "confidence": "EXTRACTED", "confidence_score": 1.0, "source_file": "lib/screens/auth_screen.dart", "source_location": null, "weight": 1.0}, {"source": "d_travelbuddy_lib_screens_auth_screen_dart", "target": "screens_auth_screen_initialized", "relation": "defines", "confidence": "EXTRACTED", "confidence_score": 1.0, "source_file": "lib/screens/auth_screen.dart", "source_location": null, "weight": 1.0}, {"source": "d_travelbuddy_lib_screens_auth_screen_dart", "target": "static_bool", "relation": "references", "confidence": "EXTRACTED", "confidence_score": 1.0, "source_file": "lib/screens/auth_screen.dart", "source_location": null, "weight": 1.0, "context": "variable_type"}, {"source": "d_travelbuddy_lib_screens_auth_screen_dart", "target": "screens_auth_screen_createstate", "relation": "defines", "confidence": "EXTRACTED", "confidence_score": 1.0, "source_file": "lib/screens/auth_screen.dart", "source_location": null, "weight": 1.0}, {"source": "d_travelbuddy_lib_screens_auth_screen_dart", "target": "screens_auth_screen_signinwithgoogle", "relation": "defines", "confidence": "EXTRACTED", "confidence_score": 1.0, "source_file": "lib/screens/auth_screen.dart", "source_location": null, "weight": 1.0}, {"source": "d_travelbuddy_lib_screens_auth_screen_dart", "target": "screens_auth_screen_build", "relation": "defines", "confidence": "EXTRACTED", "confidence_score": 1.0, "source_file": "lib/screens/auth_screen.dart", "source_location": null, "weight": 1.0}, {"source": "d_travelbuddy_lib_screens_auth_screen_dart", "target": "screens_auth_screen_featurechip", "relation": "defines", "confidence": "EXTRACTED", "confidence_score": 1.0, "source_file": "lib/screens/auth_screen.dart", "source_location": null, "weight": 1.0}, {"source": "d_travelbuddy_lib_screens_auth_screen_dart", "target": "package_flutter_material_dart", "relation": "imports", "confidence": "EXTRACTED", "confidence_score": 1.0, "source_file": "lib/screens/auth_screen.dart", "source_location": null, "weight": 1.0}, {"source": "d_travelbuddy_lib_screens_auth_screen_dart", "target": "package_flutter_foundation_dart", "relation": "imports", "confidence": "EXTRACTED", "confidence_score": 1.0, "source_file": "lib/screens/auth_screen.dart", "source_location": null, "weight": 1.0}, {"source": "d_travelbuddy_lib_screens_auth_screen_dart", "target": "package_firebase_auth_firebase_auth_dart", "relation": "imports", "confidence": "EXTRACTED", "confidence_score": 1.0, "source_file": "lib/screens/auth_screen.dart", "source_location": null, "weight": 1.0}, {"source": "d_travelbuddy_lib_screens_auth_screen_dart", "target": "package_google_sign_in_google_sign_in_dart", "relation": "imports", "confidence": "EXTRACTED", "confidence_score": 1.0, "source_file": "lib/screens/auth_screen.dart", "source_location": null, "weight": 1.0}, {"source": "d_travelbuddy_lib_screens_auth_screen_dart", "target": "package_google_fonts_google_fonts_dart", "relation": "imports", "confidence": "EXTRACTED", "confidence_score": 1.0, "source_file": "lib/screens/auth_screen.dart", "source_location": null, "weight": 1.0}, {"source": "d_travelbuddy_lib_screens_auth_screen_dart", "target": "home_screen_dart", "relation": "imports", "confidence": "EXTRACTED", "confidence_score": 1.0, "source_file": "lib/screens/auth_screen.dart", "source_location": null, "weight": 1.0}]}